torchgan/__init__.py
torchgan/models.py
pytorchgan-0.0.2.dist-info/LICENSE
pytorchgan-0.0.2.dist-info/METADATA
pytorchgan-0.0.2.dist-info/WHEEL
pytorchgan-0.0.2.dist-info/top_level.txt
pytorchgan-0.0.2.dist-info/RECORD
