Metadata-Version: 2.1
Name: pytorchgan
Version: 0.0.2
Summary: PytorchGAN是一个基于Pytorch框架的生成对抗网络（GAN）实现库。
Home-page: https://github.com/xuehangcang/pytorchgan
Author: Xuehang Cang
Author-email: xuehangcang@outlook.com
Keywords: pypi,python,Pytorch,GAN
Classifier: Programming Language :: Python :: 3
Classifier: Operating System :: Unix
Classifier: Operating System :: MacOS :: MacOS X
Classifier: Operating System :: Microsoft :: Windows
License-File: LICENSE
Requires-Dist: torch
Requires-Dist: torchaudio
